{
  "ok": 0,
  "msg": "",
  "data": {
    "list": [
      {
        "id": 2149413,
        "uid": 3786400,
        "r_reply_uid": 3650146,
        "post_id": 110700,
        "reply_id": 0,
        "floor": 1,
        "great": 0,
        "cnt_zan_rcv": 0,
        "created_at": "2022-11-12 13:51:04",
        "text": "我的阳极说发了，过了两天才收到推送，不好评价这个事",
        "content": "<p>我的阳极说发了，过了两天才收到推送，不好评价这个事</p>",
        "has_zan": 0,
        "manage_menu": [
          {
            "name": "分享评论",
            "api": "",
            "event": "shareReply",
            "confirm": ""
          },
          {
            "name": "举报此内容",
            "action": "report",
            "event": "report",
            "api": "/api/abuse-report?id=2149413&type=13",
            "confirm": "确认举报？"
          }
        ],
        "past_time": "2022.11.12",
        "user": {
          "id": 3786400,
          "nickname": "豆酱",
          "bio": "这个玩家显然是想保持一些神秘感，没留下什么话",
          "avatar_path": "https://img.zfrontier.com/avatar/220212/ava620700dc6836e",
          "verify_class": "",
          "verify_info": "",
          "bbs_lv": 5,
          "level_name": "U571",
          "hash_id": "zaB5Ko5dEqBvD0",
          "view_url": "/app/user/zaB5Ko5dEqBvD0",
          "xmas_hat": 0
        },
        "sub_replies": {
          "list": [],
          "total": 1,
          "has_more": false
        }
      },
      {
        "id": 2149426,
        "uid": 3420630,
        "r_reply_uid": 3650146,
        "post_id": 110700,
        "reply_id": 0,
        "floor": 2,
        "great": 0,
        "cnt_zan_rcv": 0,
        "created_at": "2022-11-12 13:56:42",
        "text": "我的上午发了",
        "content": "<p>我的上午发了</p>",
        "has_zan": 0,
        "manage_menu": [
          {
            "name": "分享评论",
            "api": "",
            "event": "shareReply",
            "confirm": ""
          },
          {
            "name": "举报此内容",
            "action": "report",
            "event": "report",
            "api": "/api/abuse-report?id=2149426&type=13",
            "confirm": "确认举报？"
          }
        ],
        "past_time": "2022.11.12",
        "user": {
          "id": 3420630,
          "nickname": "omen",
          "bio": "这个玩家显然是想保持一些神秘感，没留下什么话",
          "avatar_path": "https://img.zfrontier.com/ava/20240724/zf66a0adae277f7",
          "verify_class": "",
          "verify_info": "",
          "bbs_lv": 8,
          "level_name": "红色十月",
          "hash_id": "m7JvVQXa8175Ez",
          "view_url": "/app/user/m7JvVQXa8175Ez",
          "xmas_hat": 0
        },
        "sub_replies": {
          "list": [],
          "total": 1,
          "has_more": false
        }
      },
      {
        "id": 2149482,
        "uid": 3443539,
        "r_reply_uid": 3650146,
        "post_id": 110700,
        "reply_id": 0,
        "floor": 4,
        "great": 0,
        "cnt_zan_rcv": 1,
        "created_at": "2022-11-12 14:19:24",
        "text": "更新的问题吧，12号上午收到顺丰推送了",
        "content": "<p>更新的问题吧，12号上午收到顺丰推送了</p>",
        "has_zan": 0,
        "manage_menu": [
          {
            "name": "分享评论",
            "api": "",
            "event": "shareReply",
            "confirm": ""
          },
          {
            "name": "举报此内容",
            "action": "report",
            "event": "report",
            "api": "/api/abuse-report?id=2149482&type=13",
            "confirm": "确认举报？"
          }
        ],
        "past_time": "2022.11.12",
        "user": {
          "id": 3443539,
          "nickname": "刚入坑",
          "bio": "这个玩家显然是想保持一些神秘感，没留下什么话",
          "avatar_path": "https://img.zfrontier.com/ava/20210125/cp600e54ccbca33",
          "verify_class": "",
          "verify_info": "",
          "bbs_lv": 6,
          "level_name": "K19",
          "hash_id": "kb2wRGrGboONK",
          "view_url": "/app/user/kb2wRGrGboONK",
          "xmas_hat": 0
        },
        "sub_replies": {
          "list": [],
          "total": 0,
          "has_more": false
        }
      },
      {
        "id": 2149491,
        "uid": 2278382,
        "r_reply_uid": 3650146,
        "post_id": 110700,
        "reply_id": 0,
        "floor": 5,
        "great": 0,
        "cnt_zan_rcv": 1,
        "created_at": "2022-11-12 14:23:16",
        "text": "不想让你赚那100罢了",
        "content": "<p>不想让你赚那100罢了</p>",
        "has_zan": 0,
        "manage_menu": [
          {
            "name": "分享评论",
            "api": "",
            "event": "shareReply",
            "confirm": ""
          },
          {
            "name": "举报此内容",
            "action": "report",
            "event": "report",
            "api": "/api/abuse-report?id=2149491&type=13",
            "confirm": "确认举报？"
          }
        ],
        "past_time": "2022.11.12",
        "user": {
          "id": 2278382,
          "nickname": "Ruka",
          "bio": "中国客制化早已经死了",
          "avatar_path": "https://img.zfrontier.com/ava/20210306/zf60439c9c497e1",
          "verify_class": "",
          "verify_info": "",
          "bbs_lv": 7,
          "level_name": "深海挑战者",
          "hash_id": "WZ1dLoxvOV0Ya",
          "view_url": "/app/user/WZ1dLoxvOV0Ya",
          "xmas_hat": 0
        },
        "sub_replies": {
          "list": [],
          "total": 0,
          "has_more": false
        }
      },
      {
        "id": 2149664,
        "uid": 32083,
        "r_reply_uid": 3650146,
        "post_id": 110700,
        "reply_id": 0,
        "floor": 6,
        "great": 0,
        "cnt_zan_rcv": 0,
        "created_at": "2022-11-12 15:18:39",
        "text": "我的发出来了啊，双11顺丰那边理解一下呗",
        "content": "<p>我的发出来了啊，双11顺丰那边理解一下呗</p>",
        "has_zan": 0,
        "manage_menu": [
          {
            "name": "分享评论",
            "api": "",
            "event": "shareReply",
            "confirm": ""
          },
          {
            "name": "举报此内容",
            "action": "report",
            "event": "report",
            "api": "/api/abuse-report?id=2149664&type=13",
            "confirm": "确认举报？"
          }
        ],
        "past_time": "2022.11.12",
        "user": {
          "id": 32083,
          "nickname": "萨瓦拉超级大光头",
          "bio": "这个玩家显然是想保持一些神秘感，没留下什么话",
          "avatar_path": "https://img.zfrontier.com/ava/20200531/cp5ed28345ee422",
          "verify_class": "",
          "verify_info": "",
          "bbs_lv": 5,
          "level_name": "U571",
          "hash_id": "MVWWDXk2DOkr",
          "view_url": "/app/user/MVWWDXk2DOkr",
          "xmas_hat": 0
        },
        "sub_replies": {
          "list": [],
          "total": 0,
          "has_more": false
        }
      },
      {
        "id": 2149901,
        "uid": 3825840,
        "r_reply_uid": 3650146,
        "post_id": 110700,
        "reply_id": 0,
        "floor": 7,
        "great": 0,
        "cnt_zan_rcv": 0,
        "created_at": "2022-11-12 16:43:30",
        "text": "原来还有2，3群群友买了，4群快成死群了，5群还活跃一些",
        "content": "<p>原来还有2，3群群友买了，4群快成死群了，5群还活跃一些</p>",
        "has_zan": 0,
        "manage_menu": [
          {
            "name": "分享评论",
            "api": "",
            "event": "shareReply",
            "confirm": ""
          },
          {
            "name": "举报此内容",
            "action": "report",
            "event": "report",
            "api": "/api/abuse-report?id=2149901&type=13",
            "confirm": "确认举报？"
          }
        ],
        "past_time": "2022.11.12",
        "user": {
          "id": 3825840,
          "nickname": "一灿",
          "bio": "声优",
          "avatar_path": "https://img.zfrontier.com/ava/20221022/zf6353a58697469",
          "verify_class": "",
          "verify_info": "",
          "bbs_lv": 3,
          "level_name": "鹦鹉螺",
          "hash_id": "55by1ejxzYrrwB",
          "view_url": "/app/user/55by1ejxzYrrwB",
          "xmas_hat": 0
        },
        "sub_replies": {
          "list": [
            {
              "id": 2149908,
              "uid": 3650146,
              "r_reply_uid": 3825840,
              "post_id": 110700,
              "reply_id": 2149901,
              "floor": 0,
              "great": 0,
              "cnt_zan_rcv": 0,
              "created_at": "2022-11-12 16:46:03",
              "text": "是这样的",
              "content": "<p>是这样的</p>",
              "has_zan": 0,
              "manage_menu": [
                {
                  "name": "分享评论",
                  "api": "",
                  "event": "shareReply",
                  "confirm": ""
                },
                {
                  "name": "举报此内容",
                  "action": "report",
                  "event": "report",
                  "api": "/api/abuse-report?id=2149908&type=13",
                  "confirm": "确认举报？"
                }
              ],
              "past_time": "2022.11.12",
              "user": {
                "id": 3650146,
                "nickname": "Ger",
                "bio": "这个玩家显然是想保持一些神秘感，没留下什么话",
                "avatar_path": "https://img.zfrontier.com/avatar/210805/ava610b873bc59cf",
                "verify_class": "",
                "verify_info": "",
                "bbs_lv": 3,
                "level_name": "鹦鹉螺",
                "hash_id": "DpRR69wBXjo5Jw",
                "view_url": "/app/user/DpRR69wBXjo5Jw",
                "xmas_hat": 0
              },
              "reply_to_user": {
                "id": 3825840,
                "nickname": "一灿",
                "bio": "声优",
                "avatar_path": "https://img.zfrontier.com/ava/20221022/zf6353a58697469",
                "verify_class": "",
                "verify_info": "",
                "bbs_lv": 3,
                "level_name": "鹦鹉螺",
                "hash_id": "55by1ejxzYrrwB",
                "view_url": "/app/user/55by1ejxzYrrwB",
                "xmas_hat": 0
              }
            }
          ],
          "total": 1,
          "has_more": false
        }
      },
      {
        "id": 2150009,
        "uid": 3675041,
        "r_reply_uid": 3650146,
        "post_id": 110700,
        "reply_id": 0,
        "floor": 8,
        "great": 0,
        "cnt_zan_rcv": 0,
        "created_at": "2022-11-12 17:24:13",
        "text": "发了，但是单号没更新没推送也是正常的，有时候我是第二天才收到，等两天没有再去问，没有就补发呗",
        "content": "<p>发了，但是单号没更新没推送也是正常的，有时候我是第二天才收到，等两天没有再去问，没有就补发呗</p>",
        "has_zan": 0,
        "manage_menu": [
          {
            "name": "分享评论",
            "api": "",
            "event": "shareReply",
            "confirm": ""
          },
          {
            "name": "举报此内容",
            "action": "report",
            "event": "report",
            "api": "/api/abuse-report?id=2150009&type=13",
            "confirm": "确认举报？"
          }
        ],
        "past_time": "2022.11.12",
        "user": {
          "id": 3675041,
          "nickname": "L9NB",
          "bio": "这个玩家显然是想保持一些神秘感，没留下什么话",
          "avatar_path": "https://img.zfrontier.com/avatar/210911/ava613c9e759e1e6",
          "verify_class": "",
          "verify_info": "",
          "bbs_lv": 5,
          "level_name": "U571",
          "hash_id": "nWQOGRbGpp7q2",
          "view_url": "/app/user/nWQOGRbGpp7q2",
          "xmas_hat": 0
        },
        "sub_replies": {
          "list": [],
          "total": 0,
          "has_more": false
        }
      },
      {
        "id": 2150213,
        "uid": 3578513,
        "r_reply_uid": 3650146,
        "post_id": 110700,
        "reply_id": 0,
        "floor": 9,
        "great": 0,
        "cnt_zan_rcv": 0,
        "created_at": "2022-11-12 18:37:02",
        "text": "今早收到推送的，我是无所谓了",
        "content": "<p>今早收到推送的，我是无所谓了</p>",
        "has_zan": 0,
        "manage_menu": [
          {
            "name": "分享评论",
            "api": "",
            "event": "shareReply",
            "confirm": ""
          },
          {
            "name": "举报此内容",
            "action": "report",
            "event": "report",
            "api": "/api/abuse-report?id=2150213&type=13",
            "confirm": "确认举报？"
          }
        ],
        "past_time": "2022.11.12",
        "user": {
          "id": 3578513,
          "nickname": "杠就你全对",
          "bio": "这个玩家显然是想保持一些神秘感，没留下什么话",
          "avatar_path": "//avatar.zfrontier.cn/g/4918b62c6a4e540d5848489183457ebe",
          "verify_class": "",
          "verify_info": "",
          "bbs_lv": 5,
          "level_name": "U571",
          "hash_id": "DpjVNz5Q7DBvOW",
          "view_url": "/app/user/DpjVNz5Q7DBvOW",
          "xmas_hat": 0
        },
        "sub_replies": {
          "list": [],
          "total": 0,
          "has_more": false
        }
      },
      {
        "id": 2150304,
        "uid": 3802990,
        "r_reply_uid": 3650146,
        "post_id": 110700,
        "reply_id": 0,
        "floor": 10,
        "great": 0,
        "cnt_zan_rcv": 0,
        "created_at": "2022-11-12 19:12:32",
        "text": "我的3.0北京发货一天了还没推送",
        "content": "<p>我的3.0北京发货一天了还没推送<img class=\"editor-image\" data-type=\"meme\" src=\"//img.zfrontier.com/emo/20220503/FmbadhVAqZB-UHsiizTpZ3T9wqrE\" /></p>",
        "has_zan": 0,
        "manage_menu": [
          {
            "name": "分享评论",
            "api": "",
            "event": "shareReply",
            "confirm": ""
          },
          {
            "name": "举报此内容",
            "action": "report",
            "event": "report",
            "api": "/api/abuse-report?id=2150304&type=13",
            "confirm": "确认举报？"
          }
        ],
        "past_time": "2022.11.12",
        "user": {
          "id": 3802990,
          "nickname": "玩坦克",
          "bio": "这个玩家显然是想保持一些神秘感，没留下什么话",
          "avatar_path": "https://img.zfrontier.com/avatar/220312/ava622bead9c3d6c",
          "verify_class": "",
          "verify_info": "",
          "bbs_lv": 5,
          "level_name": "U571",
          "hash_id": "NVoER6Y22Axd6",
          "view_url": "/app/user/NVoER6Y22Axd6",
          "xmas_hat": 0
        },
        "sub_replies": {
          "list": [],
          "total": 0,
          "has_more": false
        }
      },
      {
        "id": 2151093,
        "uid": 3831457,
        "r_reply_uid": 3650146,
        "post_id": 110700,
        "reply_id": 0,
        "floor": 11,
        "great": 0,
        "cnt_zan_rcv": 0,
        "created_at": "2022-11-12 22:05:49",
        "text": "五鱼的发货是真发货，他确实把货都丢给快递了。。。至于你啥时候收到推送，看快递啥时候发出，更新快递信息然后还有就是双十一的问题吧，快递点要发的东西多，堆积着一堆要发，理解一下",
        "content": "<p>五鱼的发货是真发货，他确实把货都丢给快递了。。。</p><p>至于你啥时候收到推送，看快递啥时候发出，更新快递信息</p><p>然后还有就是双十一的问题吧，快递点要发的东西多，堆积着一堆要发，理解一下</p>",
        "has_zan": 0,
        "manage_menu": [
          {
            "name": "分享评论",
            "api": "",
            "event": "shareReply",
            "confirm": ""
          },
          {
            "name": "举报此内容",
            "action": "report",
            "event": "report",
            "api": "/api/abuse-report?id=2151093&type=13",
            "confirm": "确认举报？"
          }
        ],
        "past_time": "2022.11.12",
        "user": {
          "id": 3831457,
          "nickname": "段－",
          "bio": "这个玩家显然是想保持一些神秘感，没留下什么话",
          "avatar_path": "https://img.zfrontier.com/ava/20221125/zf6380cd310065a",
          "verify_class": "",
          "verify_info": "",
          "bbs_lv": 6,
          "level_name": "K19",
          "hash_id": "DprQQkl1Yb8RaB",
          "view_url": "/app/user/DprQQkl1Yb8RaB",
          "xmas_hat": 0
        },
        "sub_replies": {
          "list": [],
          "total": 0,
          "has_more": false
        }
      },
      {
        "id": 2158301,
        "uid": 3879520,
        "r_reply_uid": 3650146,
        "post_id": 110700,
        "reply_id": 0,
        "floor": 12,
        "great": 0,
        "cnt_zan_rcv": 0,
        "created_at": "2022-11-14 11:58:42",
        "text": "有没有想转单或者到手出的的，蹲一个",
        "content": "<p>有没有想转单或者到手出的的，蹲一个</p>",
        "has_zan": 0,
        "manage_menu": [
          {
            "name": "分享评论",
            "api": "",
            "event": "shareReply",
            "confirm": ""
          },
          {
            "name": "举报此内容",
            "action": "report",
            "event": "report",
            "api": "/api/abuse-report?id=2158301&type=13",
            "confirm": "确认举报？"
          }
        ],
        "past_time": "2022.11.14",
        "user": {
          "id": 3879520,
          "nickname": "霸气的昵称捏",
          "bio": "这个玩家显然是想保持一些神秘感，没留下什么话",
          "avatar_path": "https://img.zfrontier.com/ava/20221008/cp63417fdd5d88a",
          "verify_class": "",
          "verify_info": "",
          "bbs_lv": 4,
          "level_name": "Triton 3300",
          "hash_id": "m7ZnkvRdmnqlL9",
          "view_url": "/app/user/m7ZnkvRdmnqlL9",
          "xmas_hat": 0
        },
        "sub_replies": {
          "list": [],
          "total": 0,
          "has_more": false
        }
      }
    ],
    "authorZan": [],
    "foldCnt": null
  }
}